{
  "citation": "",
  "description": "",
  "features": {
    "qa_id": {
      "dtype": "string",
      "_type": "Value"
    },
    "passage_id": {
      "dtype": "string",
      "_type": "Value"
    },
    "question": {
      "dtype": "string",
      "_type": "Value"
    },
    "answer": {
      "dtype": "string",
      "_type": "Value"
    },
    "question_type": {
      "dtype": "string",
      "_type": "Value"
    },
    "difficulty": {
      "dtype": "string",
      "_type": "Value"
    },
    "macro_domain": {
      "dtype": "string",
      "_type": "Value"
    }
  },
  "homepage": "",
  "license": ""
}